{
  "name": "Ubuntu",
  "image": "mcr.microsoft.com/devcontainers/base:jammy",
  "features": {
    "ghcr.io/devcontainers/features/aws-cli:1": {
      "version": "latest"
    },
    "ghcr.io/devcontainers/features/node:1": {
      "nodeGypDependencies": true,
      "installYarnUsingApt": true,
      "version": "lts",
      "pnpmVersion": "latest",
      "nvmVersion": "latest"
    }
  },
  "customizations": {
    "vscode": {
      "extensions": [
        "amazonwebservices.amazon-q-vscode",
        "amazonwebservices.aws-toolkit-vscode",
        "angular.ng-template",
        "dbaeumer.vscode-eslint",
        "esbenp.prettier-vscode",
        "github.vscode-pull-request-github"
      ]
    }
  }
}
